cc_pathplanner/angles.py
cc_pathplanner/convert_coordinates.py
cc_pathplanner/coverage_path_planner.py
cc_pathplanner/dubins_path_planner.py
cc_pathplanner/field.py
cc_pathplanner/lines.py
cc_pathplanner/main.py
cc_pathplanner-0.1.0.dist-info/LICENSE
cc_pathplanner-0.1.0.dist-info/METADATA
cc_pathplanner-0.1.0.dist-info/WHEEL
cc_pathplanner-0.1.0.dist-info/top_level.txt
cc_pathplanner-0.1.0.dist-info/RECORD
