Metadata-Version: 2.1
Name: cc-pathplanner
Version: 0.1.0
Summary: A package to generate a guidance trajectory for complete coverage of a region of interest
Author-email: "Ibrahim A. Hameed" <ibib@ntnu.no>, "Sanjeev Kumar R. S." <sanjeev.k.r.sudha@ntnu.no>
Project-URL: Homepage, https://github.com/sanjeevrs2000/cpp
Project-URL: Bug Tracker, https://github.com/sanjeevrs2000/cpp/issues
Classifier: Programming Language :: Python :: 3
Classifier: License :: OSI Approved :: MIT License
Classifier: Operating System :: OS Independent
Requires-Python: >=3.7
License-File: LICENSE
